odoo/addons/l10n_ro_fiscal_validation/README.rst
odoo/addons/l10n_ro_fiscal_validation/__init__.py
odoo/addons/l10n_ro_fiscal_validation/__manifest__.py
odoo/addons/l10n_ro_fiscal_validation/data/res_partner_vat_cron.xml
odoo/addons/l10n_ro_fiscal_validation/examples/res.partner.csv
odoo/addons/l10n_ro_fiscal_validation/i18n/l10n_ro_fiscal_validation.pot
odoo/addons/l10n_ro_fiscal_validation/models/__init__.py
odoo/addons/l10n_ro_fiscal_validation/models/res_partner.py
odoo/addons/l10n_ro_fiscal_validation/readme/CONTRIBUTORS.rst
odoo/addons/l10n_ro_fiscal_validation/readme/DESCRIPTION.rst
odoo/addons/l10n_ro_fiscal_validation/readme/INSTALL.rst
odoo/addons/l10n_ro_fiscal_validation/readme/USAGE.rst
odoo/addons/l10n_ro_fiscal_validation/static/description/icon.png
odoo/addons/l10n_ro_fiscal_validation/static/description/index.html
odoo/addons/l10n_ro_fiscal_validation/tests/__init__.py
odoo/addons/l10n_ro_fiscal_validation/tests/test_partner_update_vat_subjected.py
odoo13_addon_l10n_ro_fiscal_validation-13.0.1.0.1.dist-info/METADATA
odoo13_addon_l10n_ro_fiscal_validation-13.0.1.0.1.dist-info/WHEEL
odoo13_addon_l10n_ro_fiscal_validation-13.0.1.0.1.dist-info/top_level.txt
odoo13_addon_l10n_ro_fiscal_validation-13.0.1.0.1.dist-info/RECORD
